{"paths":{"0":["music/BGM_MG",7],"1":["res/spine/jinzita_kuang",0],"2":["res/bg/tankuang",0],"3":["res/symbol/BgGroup",0],"4":["res/粒子/slots_win_lizi6",5],"5":["res/free/light",0],"6":["music/Link",7],"7":["music/Reel_run",7],"8":["res/spine/jinzita",11],"9":["res/bg/1113_1",0],"10":["res/symbol/symbolGroup",0],"11":["CommonRes/UIimg/yes",0],"12":["res/light/fireani",0],"13":["music/Fiop1",7],"14":["CommonRes/UIimg/home",0],"15":["res/symbol/symbolfree",0],"16":["res/spine/win",11],"17":["res/bg/FG_BG_L",0],"18":["res/bg/BgGroup1",0],"19":["music/Reel_Stop",7],"20":["music/Scatter2",7],"21":["music/Transfer_fast",7],"22":["CommonRes/coin/effCoin",5],"23":["res/spine/shousuo",11],"24":["CommonRes/coin/Coin_tex",0],"25":["res/font/minimun_num",0],"26":["res/font/CongratsNum_0",0],"27":["res/free/light0",0],"28":["music/Free_02",7],"29":["res/spine/liudong",11],"30":["music/Button_On",7],"31":["res/free/Common_Btn_Green",0],"32":["res/bg/logo_en",0],"33":["res/bg/topbg",0],"34":["res/spine/falao",11],"35":["res/spine/xuanzhuan",11],"36":["music/Small_win_01",7],"37":["CommonRes/UIimg/no",0],"38":["res/font/brand_num",0],"39":["res/spine/saoguang",0],"40":["res/spine/jinzita",0],"41":["CommonRes/UIimg/mobUi",0],"42":["music/Guide_Voice",7],"43":["res/free/WinMore_Popular_Cell_Bubble_Hot",0],"44":["music/Transfer",7],"45":["music/Fiop3",7],"46":["res/spine/xuanwo",0],"47":["res/font/Num_Upgrade_0",0],"48":["res/spine/xuanzhuan",0],"49":["res/粒子/slots_win_jb6",5],"50":["res/bg/Backpack_GetCard_Bg",0],"51":["music/Combo_f_x3",7],"52":["music/Small_win_02",7],"53":["res/symbol/13fdf0032.dae4c",0],"54":["music/ChangeWin",7],"55":["music/Fiop2",7],"56":["music/Combo_f",7],"57":["music/Combo_f_x2",7],"58":["music/Scatter_bell",7],"59":["music/Combo_Declare",7],"60":["music/change",7],"61":["res/free/Notification_Icon_06",0],"62":["res/spine/baozha",0],"63":["res/free/AutoPlay_BtnBet_Hover",0],"64":["res/font/Combo_o",0],"65":["music/FG_End",7],"66":["music/Scatter1",7],"67":["res/spine/xzguang",0],"68":["music/Combo_f_x4",7],"69":["res/spine/shousuo",0],"70":["music/FlyBug",7],"71":["CommonRes/UIimg/bottomComon",0],"72":["res/light/1d8ae575a.fd33d",0],"73":["music/Link_fast",7],"74":["res/wordimg/wordGroup",0],"75":["music/Combo_f2",7],"76":["music/Fiop4",7],"77":["res/spine/saoguang",11],"78":["res/粒子/slots_win_lizi8",0],"79":["res/bg/backicon",0],"80":["res/spine/liudong",0],"81":["music/Big_win",7],"82":["music/FG_Go",7],"83":["music/FG_way_up",7],"84":["music/Big_win_end",7],"85":["res/粒子/slots_win_lizi6",0],"86":["res/spine/jinzita_kuang",11],"87":["res/font/Num_Freespine_0",0],"88":["res/spine/falao",0],"89":["res/font/freespins",0],"90":["res/free/default_btn_pressed",0],"91":["res/bg/1113_0",0],"92":["res/bg/mainBgGroup",0],"93":["res/bigwin/BigWinGroup",0],"94":["res/bg/MG_BG_L",0],"95":["res/font/ways_num",0],"96":["res/free/BuyBonus_ItemIcon",0],"97":["music/Spin",7],"98":["res/spine/baozha",11],"99":["res/wordimg/freeWord",0],"100":["music/MG_NearWin",7],"101":["res/粒子/slots_win_lizi8",5],"102":["res/spine/xuanwo",11],"103":["res/spine/bgguang",11],"104":["res/free/BuyBonus_Hot_Bubble",0],"105":["res/spine/xzguang",11],"106":["music/Scatter3",7],"107":["res/粒子/slots_win_jb6",0],"108":["music/BGM_FG",7],"109":["res/spine/bgguang",0],"110":["music/Small_win_03",7],"111":["res/free/Common_Btn_Dark_2",0],"112":["res/free/Common_X",0],"113":["music/FG_getbug",7],"114":["CommonRes/font/SHOWG",6],"115":["CommonRes/coin/coin",0],"116":["res/spine/win",0],"117":["res/bg/Intro_Feature_LT_02",0],"118":["music/Collection",7],"119":["res/light/fireani",1],"120":["res/wordimg/freeWord",1],"121":["res/spine/baozha",2,1],"122":["res/bg/Backpack_GetCard_Bg",2,1],"123":["res/light/1d8ae575a.fd33d",1],"124":["res/spine/win",2,1],"125":["res/spine/jinzita",2,1],"126":["res/spine/jinzita_kuang",2,1],"127":["res/animation/betchange",8],"128":["res/spine/liudong",10],"129":["res/free/default_btn_pressed",2,1],"130":["res/font/ways_num",9],"131":["res/animation/bigwininit",8],"132":["res/bg/backicon",2,1],"133":["res/bg/1113_0",2,1],"134":["res/粒子/slots_win_jb6",2,1],"135":["CommonRes/UIimg/home",2,1],"136":["res/free/light",2,1],"137":["res/animation/showbigwin",8],"138":["res/animation/collectlight",8],"139":["res/font/minimun_num",9],"140":["res/animation/betdispear",8],"141":["res/free/light0",2,1],"142":["res/font/brand_num",2,1],"143":["res/animation/bigwinend",8],"144":["res/animation/betshow",8],"145":["res/spine/xzguang",10],"146":["res/free/BuyBonus_ItemIcon",2,1],"147":["res/bg/1113_1",2,1],"148":["res/font/freespins",9],"149":["res/animation/wildlight",8],"150":["res/wordimg/wordGroup",1],"151":["res/spine/xuanzhuan",10],"152":["res/spine/bgguang",2,1],"153":["res/font/brand_num",9],"154":["res/spine/win",10],"155":["res/bg/BgGroup1",1],"156":["CommonRes/coin/Coin_tex",4],"157":["res/symbol/13fdf0032.dae4c",1],"159":["res/bg/mainBgGroup",1],"160":["res/spine/jinzita",10],"161":["res/free/AutoPlay_BtnBet_Hover",2,1],"162":["res/free/WinMore_Popular_Cell_Bubble_Hot",2,1],"163":["res/free/Common_Btn_Green",2,1],"164":["res/粒子/slots_win_lizi6",2,1],"165":["res/symbol/symbolfree",1],"167":["res/spine/xzguang",2,1],"168":["res/spine/liudong",2,1],"169":["res/bg/FG_BG_L",2,1],"170":["res/animation/symfade",8],"171":["res/free/Common_Btn_Dark_2",2,1],"172":["res/spine/saoguang",10],"173":["res/font/ways_num",2,1],"174":["res/animation/bigwinloop",8],"175":["res/font/Combo_o",2,1],"176":["res/spine/bgguang",10],"177":["res/font/Num_Upgrade_0",2,1],"178":["res/bigwin/BigWinGroup",1],"179":["CommonRes/UIimg/yes",2,1],"180":["res/spine/baozha",10],"181":["res/free/Common_X",2,1],"183":["res/animation/betlooplight",8],"184":["res/spine/shousuo",10],"185":["CommonRes/coin/Coin_tex",2,1],"186":["CommonRes/UIimg/bottomComon",1],"187":["res/bg/Intro_Feature_LT_02",2,1],"188":["res/font/Num_Freespine",9],"189":["res/font/freespins",2,1],"190":["res/symbol/BgGroup",1],"191":["res/spine/xuanwo",2,1],"192":["res/粒子/slots_win_lizi8",2,1],"193":["res/spine/xuanzhuan",2,1],"194":["res/free/BuyBonus_Hot_Bubble",2,1],"195":["res/font/Num_Upgrade",9],"197":["res/animation/fireani",8],"198":["res/font/CongratsNum_0",2,1],"199":["res/font/CongratsNum",9],"200":["res/spine/falao",2,1],"201":["res/spine/jinzita_kuang",10],"202":["res/free/Notification_Icon_06",2,1],"203":["res/bg/tankuang",2,1],"204":["CommonRes/coin/coin",2,1],"205":["res/spine/xuanwo",10],"207":["CommonRes/UIimg/mobUi",1],"209":["res/bg/MG_BG_L",2,1],"210":["res/font/Combo_o",9],"212":["res/spine/falao",10],"213":["res/animation/addlight",8],"214":["res/font/Num_Freespine_0",2,1],"215":["res/bg/topbg",2,1],"217":["CommonRes/coin/Coin_ske",3],"218":["res/bg/logo_en",2,1],"219":["res/symbol/symbolGroup",1],"220":["res/animation/shakeItem",8],"221":["res/font/minimun_num",2,1],"222":["res/spine/saoguang",2,1],"223":["CommonRes/UIimg/no",2,1],"224":["res/spine/shousuo",2,1]},"types":["cc.Texture2D","cc.SpriteAtlas","cc.SpriteFrame","dragonBones.DragonBonesAsset","dragonBones.DragonBonesAtlasAsset","cc.ParticleAsset","cc.TTFFont","cc.AudioClip","cc.AnimationClip","cc.BitmapFont","sp.SkeletonData","cc.Asset"],"uuids":["022+FsrYlFMYVcww5qEB4T","03fyrLGbNBjKr5vYgcIHwu","05Sa1aMgFFq75Ra7nZAGv7","057jue6LdPm7Vc6OxWQSIi","078h3TamVAu7uk+BP0Nrt1","0aMhw9khBKsKnLwojK0oX8","0dpJw9CDhBN6b2RHDtRH4z","0ezd/+CX5OXonq08PFeGoO","0e82fg9DNF/LJFq5WPCf6b","10I4W9CaJEjL4vDvYrFMNO","12IDvetRhIpKRLmiyP/Z0h","14oIAojXBDRYVnP7REuJvZ","17mBxAILZE7ZzO17+32XId","191w5BmdpMYYshM24wQJuX","1d+2s7BzVBXru9YHc8CxdR","20x7y3aqNKbaHWHIHSr3yg","20+1rvXbpMu4VmwPvKsljy","24NJ+3JRhCV6Ut/OAJDyBi","26ASvT5blB+oqhCsUb5tg+","26ItejsFxGBZIDtZNKOx/D","27irPwItdBfpOkeuNXeGKp","2cFrWK3PtNKrylIfumS2cM","2fxuPFW2dFL6jnBSsfXzNb","33srMyPYVNPLTQFAHsRi03","35u5zCIVBJNoO/x1trK1kW","36KVcnuxVOto+xArSeu3W4","3aPPZZCLpJ15nZhZ+hiFRu","3abQnFyANNWKUwyDfZnn10","3bFoE6OmFFvITCFUasGiii","3dCRG/EuZFG76KV/iCN39F","3evRpqgO5Eyqh2v5tbbfRv","43G62cq81A47CJ2PUYz5in","43rfbrvjxGz4BaD7RBhZWm","44KTD3EB1HKbIcAuVRwCGB","44Q0wC/FdNX5R699NqgGxU","45WzxoVjJMrIIfnNnx2tZv","49Dwhy8YdJRLC3Ee1FOdma","4a7172slZA/7O5JbMZbkpi","4cVvb2ZoFG6qAQT+XP073Y","51nFZujotFGY3pzb6aTbwO","52Zxu2J6FGqKdzKemaLG/9","52tlEw1FRLlb4gvGZqf7MQ","55JUjRUcpB2rMNIbkeuULT","55hwhQ371DXZ+goJeDv3Pe","563d5HM0xFcr2e1jtTK52T","5695sm5uNO/qgPzfGSnrod","57Gjiqli5HHa5TkFWKYD9g","57k3rregtAZrQACx61SuMU","5a7v8Rr9REU5MOkN1PQYsQ","5beBrcE9xIHqjQCqn03vz0","615BgzPJBAKLp29IkP0GgD","63hNpvow5DXZ8VIgb6Q/bM","692wNfnwtFYZT5OdaLqG1f","6dnurx3chMpaZ4hHX7MPRz","6e3IE9iz5Ir4iJ/hk045TS","75F+aDgKZCiIt8IucjBbf4","77kom9kftHoL2UPmCJVy3o","78zHhHm8BCLqOud6jCf6Ww","79yz733QdB87fdV751ZiYS","7c1Yv8lIRA/aLo1rUZHa7I","7e/Wd+C2dBTKpyVVCEvcak","80EYakELtK2q7IWHeiMJuN","81ovCyDOZORbuOdG2O+4BP","81+iUq0c5I9aBooyfbYNmy","83Qf1Q70pLKLa8cfwsi3jt","83yQHMI5NJJpDGx6qnlZq2","8bsDitMMxL3LTwdD4PfwPJ","8cvafq42tGNaJcCLwmJkK2","9155KautdB9rzk5Yf575o+","99cM0ftWJI3osAF2W2P8CN","9bri8KgNlAfLMOocpvLmJa","9cyPaAHo9FiKTi6M8gfRPC","9c5GwHql9AD6u7hPdQYher","a1RTdohpFFv5ZX3X1YCO+F","a1hBtN+WdMF5rYVSpcRxa/","a6tWf9ZztKGoCmSFOyeyA3","abnPXEA2NLZqOB+M+0ii1P","adBzahjnNOGZr7Jln+jmp5","aerTLxKJ5GGI1pG9LNG2of","b4n7p+SwxPyLO30pUwK2kg","b5gjPi64FHhJ301yd9dVlE","b827orpdJFYKXyX56GbUge","baJvGW8TBM+IxdnRJorF2w","baKVGZKpZNtLMxWtMtOep6","beqXLwScZEaKvl9G/6wiEm","bfgSdVBfRPhrdkcGKkjNLu","bfs0YEVIFCD7fLKA2lhSYm","c1BGwoJrNDYJlVjVTgNnDn","c1kPK2z8dF2YEVG0JSnFfn","c2Dc3/OhNNma9aW9Q7sWSA","c21NMOv0ZBH4noD0m/jDlU","c5T07jLHNL9qGilEezqXh6","cdOQblGr5Fx4FFSVkVTjM3","cdgoeN1qZAp5nfGFywiPnF","ceMuCek0BPqbNrbNXu82m3","ceOK3cM2FOooKd/kZZjHvC","cflRZwLnJJWKVnq5D7kkoJ","d0eB3eElpNzq6Pjqr5m4//","d1bJ3GhJVP+pgWH2j/4vn6","d20WAGNjlOQ6LvGKRbtNPG","d228LBoFZGJZ94NIk7khot","d9bOT1gV5MM5wtafanIgZN","da6EQMMGlLzpbeYS5Y/qoy","dbFnfPL7FCiLyze7AETEcW","deLkA80d9I0JKNbDsVDIzu","debopoGE9NLLD9Yl915ry9","e2xfBq3zRNyayzukjR3ejk","e281UAg0ZHm5FeuOIFzuQf","e6A6OB875FoqoZHRgrWvAJ","e7DPftIaNAmqgLTjvWLwo8","eaBJV5eJdHiIDhtGVU/N/Q","eaycDd6L5Brp4RxopvALxl","ebc1XOsBFOKqQmRuaja3PM","eb7Vw+yydD3o6xDF6em+o2","f07EQFNNdI/Jff+7vMLpIf","f2F+LfiKJOt4tr1veCq9Hf","f4F0G+1K5ES7TA+Z9+AikI","fazKOnT6JFQY1t26yc9h2q","fedQPY6etFP6e+Fi6T23wk","01QEfd5oJGZZ3M8WWSzmWt","01VQE+ERVLl7FqDV2/E1Bs","05Vzs7SUlMEZSzR5g65y7S","05iBTqklJPGqMdtQulo6G0","051S3fT9xHwaHg96JX6jse","0as6bV62hNPJ1fm8ZGFZ1O","0b4TAZG69Ik4BBDEMh3byv","0eTdHTlRNMx43QThz3+s07","11wo9FSxJAlYPXLTdIsbbv","128pZp/3lCtZyyBJfK918K","17RWQxOtlCwIxzLXqNBAd9","179is2ktdKA5Ij5+HRDaXe","18WfHnSS5HNLR9XzPGIB4x","1aIBQ+PdNOWKUPkAL4TJjl","1aTzW8hj9Eu6sh5w4Tj+HI","1bFqsyAvhEToDIAAa2ibjW","1chwu02YlMPIOcukFDilrZ","1eJjXzij5K9a4qKiyu0BUg","2cYsjtOXhCwLFpDczcy8DT","2fsPcFfodAPIfpkUOmBo2D","30FBFgogRIK5ciesoXrsPK","31KaE8ebtFO6jT2Xd4q1Lg","36YsyBtGhJF5RFFBIIATYc","37Ew0t/5xN25HAJ1ZT7Nw6","38LJFEfJFCVYpau0ewZgJ+","38eveZufZB1bb9xvrPlgQ2","3cGDjJzj1LW62L1s54LwD2","3ceyFPYjlDybNl88DC22nq","44PUxeXMtD0rNMnqD8vfWz","45FO1lLWlFLJCrtg07tXGh","45deesmZRIpo4ofoH1XoDS","47Hpby8EBAWaBiFGVB3Zjw","4aab/hCAxJEICobX8ysYPH","52To1tgQZDp5bBXCiCPwU7","58S5qbuLVP2JO8EXVTqWhM","59hQu2hllFXJLZgh1LDHqe","5aDRMHBg1JNLs3GJpDFzHq","5bBtIlOgtOFoZ4olT5xxPQ","61J7MwCndLArSkdY6BRJnU","61cyPdEfRN047sDK9rO0W5","625Q4WOHNJXI8+hlGw+wUu","6330Tks35C4aFT2/Lf5BuZ","64A/jVTPtFFJlvvo8tcjOc","6aiVbIcGZFlIwy/bmfSpx2","6aq+N3OcFKmrepMKzLPeda","6bHJgFq2pNx5M9Rn/EQ6Sz","6bbZILrllEtIuY9LnHaNNl","6fLjGmsqNJQZjxN9neVdPz","72O9KVUT9CvLgsoJ97xe7l","73db6zpYhJhJEtaM1VSk91","76jBKzAxVFmLbq4FsbksNY","79RfBumvFNhZn0g/zCW0BV","7aiZKwDBRISpiP6WdkEw3K","7b4MfEazJPv7IrqsJ/etKF","7b6l7HwlNOR4gmMlC5+eU3","81MqwWK7xNZYvTVO4NDaR8","83RQl5ybxMCZz6pZZKJ1zM","85TXemEupFeI/E7DNsJaqs","86wz2Aj9ZHBJMpkARG/phv","89O5w3rhFK9I+i0h+FWzOG","89hXV07jNMSqRObwnmwnyV","8a6AHyd61JTKvSamQVyd2C","8bf+Ax7ohNuK9BG3XLxK1c","92BPSSWhxNGLtL+p1gmyi9","9aL4VTcuhJNpBdmaVwaLrO","9bEI5hfrBAf76W4FWNa510","9conNt5X1H7LnLXW1HZGlf","a1YU07GStIIp4UoEx+3UKZ","a1i3CUbUtMMqHSO3n+VwAO","a3m4fUFn5MsLqlQ0xt8qua","a9UJqzIOlCzqGg+1ZzUN4s","aaoaZtYFZE+b9UYhTo+SqM","aau0YK3CtOmrKIzyJUerz+","ac1Nq6wCRJZJk9UuqOHg7i","b0F7BKgQdLTZ73qigcOfn8","b08MJXDmZJ1aqMyTbTd7IY","b1uEBjUt5Job6zrud8qdjV","b2aHrECZ5APKGS/0d2hvT1","b3DlvETeFEkIRUn3z/7X3C","b4cd4Y6uJArrZMhsUTpdSW","b8o+Cq+StPKqDQ7BUCrz5m","c0/N0RkLhEJZrSvNvoUk60","c6GLJ+NG9FuJ+/6mu/h5Eb","c82qnR5GRLzbA4xacOto2r","c9vZFp+U5Cd7TWOmxTR3zV","cbyyaCR4xI5JfdEvvl4r8B","ccMRfiqHBB4ol7uTrvqOQV","ccb6KGzshERqmvuaDy1prZ","cdxogBVvdCKKT++lQqSWJp","d0qC05vt5GxLaYyB/w3t//","d2yLt+D/NLGamhP7L1GGwr","d4/3mawi1LmaPVOI5SW0uC","d608qFRoFHwbXd0Dap056i","da/fF0dn1N548Iih3sbjlv","dbm1llHaJH9p/PHOChO8/t","de2TF0TvxIDqKjStU8PLCV","dfz3K6P79A8bPtRHX3x+FZ","e2tsSYPVxI1rHpfQZMkr95","e9zRII56NA84uTiBh8LYLy","eawafFcMtIWY5WC7P3evPg","ebKchrlPBFQKzv1MPL4/ea","ebZAVMdodAyoeqGZZb8MII","eeK0gAzDVEh715060bCzbf","f1E9cssZ5A/6xu+awqCaG9","f2q49nrZBM6rkCw8o9EARZ","f9GQkANSxLwIiyhLiBxJBO","00K4ZBgthNp4+wubdvW3JV","00SO11H1FK/KnzWD2JQy1Q","01PFMmuGpOnLUoHea6y+Dc","01VJQxQN1PtoWAa8n3VfZs","01WdxGi6pDyrWy+tLa5oRW","01YPPYluZG2LP6lSiMuk9x","01jROFBTRKNL9oQBO0AG65","01xBve5D9Avre2npDqHNOX","01zpc9XnJMCqmx7ORUFROP","02msCW7WlFIbQC5f1PXrxW","0261ngegtB9ojC1CzcuOSR","03P/yfAPNKu741ClNCU/S/","03QsOzO9pLrpe5Q1owCmpQ","038Rrdub5MrpMT7CxDA1hW","04H0IXPKRKTYRkQhC1dLe+","04sWNXcFRNVYHotKk4+qBQ","05YAUZ/1VDlICE4IHn0NmV","054dQejv9AwaZJGFJnRJxV","06IKvPKvpB84AFyp8kQroN","060Fna34pPFY1cWMgIadYt","08cMhLDP5D1aaXbyw82eYa","08+ey+xglHy5xFmtyWqIPa","09T5orNo9BP5dVYT03NiV9","09oQeZoy9O/aTLVXKgch/l","0aGk2yycFO/a5pCArpZlqi","0aJBUabmpID5ptV5UPlkqj","0aRJ5mS/lEmpi345y61ZRI","0aUEKEc4lDkr781jmbTVut","0aiXRJVntMbYn34aNXU/II","0asXltdf1Pnor2CJN00QSs","0awOPB021IXYAB6FZVI5T0","0ayx6Kn85KeKzp54tCqt1U","0bUPv4qQRLGYMlo8SI21rd","0bzd1RNJtI6a2hX+Oi/1px","0cSyxEdclP7LIvMe6qI3X4","0cffWPMUxARJjPJZxfmAmG","0dSTAUItZPiK9CzEZd+OoW","0dtwAHZRZF0YTWgBr2LNsm","0dv74JV41A4azxwdqg0u5h","0eaMle26BHYbN3s+eUiMCQ","0erEh2drZM3a5AalFUKrNW","0e2tSoTIdH85U1GFzG1hNv","0fGrbFOhdO04NTDXLc7Ws7","0ffXUcXU5CNpiJnJtiLsfW","0fpV5E07pLHaxBi+Rfgyxy","0fqjdOwRlBC5e4ptAQ2G4B","0fqsTdGaVNBqHImeEZaXjU","0fr9U50VpFarmiZJUzFJ7/","0fs6rGkDhKa6I5F879YRkd","10sWQtbaxJn7oV3GF81e6C","11L8FaYy1H0KzqcsKvsGj+","11WpJGM85B5rcI+S8qUlOR","11zkn7xIpCQY8/R24yHI48","12Yl59ymBAuZ2KIMk9rA36","127V826dVIh71y3wd20yet","12+hPPI+hPBLZ2Wk/sLTxd","13Cx5xjxpBhpWxVmEs7/Zt","13n1DTJyBEP60NPR15pBpJ","133MZ3651D2p+Yn3MrBSZW","15hl5wsi5CSZ7qvCq1jeJm","16ZexnilFKxp2xoVO0q5ds","16k4QjwWVGzIvGoB8KxdW7","16oCHinbFL7a7oL/WpjrAf","16xjwAIxlLZ5hKoodFCrfv","16/b41uY5OAZvaDwtiJTUi","17j5tMGfJGqYzLaIJXA6NZ","174S283w5A0YMaifBTaRCW","18Jt2/5yVC/q4l8yyD0q7+","18QBaioa9IGavArMf8NPSJ","19O+k29wJI1Y3EIgGJSZW0","19S36auGdP4YKB4kWoqC5Q","196kGe47FO/LuS2cj1Y9uy","1aquDsDsNK0rAWObMCfVwW","1bFD5xQ9JCbIfMmBgYrB22","1bQfTYteZKFYwHg4B3M1Kr","1bbh5elRZBPLm+UwmsLM4E","1blBM4FgNHKZ/bXomHcVpp","1bzFyywHFMtpWKOuQA+TvC","1cApM9Gx1ER6QJn3YXBtQy","1dAP5rkoVBy514pdAG/0ln","1dH+lp2GZL9qTHtuZgmKdj","1dNFt2HbpOQJkb2ltHFuMD","1dp3sUrPxMmJKiOAuF84lZ","1es3+je8JM3K6uP/YXW5m/","1ex4EKFyJGBbJvczBMIURi","1fL4khPMlFVY8vP6SWgIwm","1fkTkS59JO1IvRWy28bdm/","1f6tcMlMxOf5q8Z9/ntrms","20LF1sxuhOwIrY2GmdgOjC","20LLRrP1VNBLMaIt8uh4Bu","20rgxjnxtNhZw+NTmAROjn","20wc4RbhZE4KsMLeZIANJS","21L/qoywJNAbFX9W7N0MEC","21o6zNlZZCQ4fmfTkMXK0N","21+TuWUd1J+5m1XLJz4hZ1","22tzTsLL5HbbwI2T42/PB8","225uHTkHNA7bCNH75bazSA","23O0hgCFhFQYnmxPi+/LV0","23PkC991RB+aFYagZ3MG8g","24FG8pgkdCcrGtU9G7mL0n","244R2HZuND+auWef4vmIFR","25TgErW5RDSYm5p19y4MDK","25e2Ukq6NJHqs/GXprSheR","25n3pJ9g1DWY15O4dWkXh5","25vKNUc89HL4sd5XS0cr2P","2558/807tHNrQ9HW8KTyR9","26CGv8kIVCOp3WXBQrJbQS","267nhdf2NHF4v+ZBNY2IJv","27TfyHuIdPCpEuhjbz4dwP","29BXWv9XFDd4N43SctsrJS","29FYIk+N1GYaeWH/q1NxQO","29mRiO66FIKriDwnjqNYe+","292DOgx4hOHoIMcmKeqlId","2aAZdPmHFBabZdu245E4vy","2bB6Ar6lZA5qbdVZwpfL3W","2b5UuWxClL5YbJl/aQmYdv","2b+EN8omBLaKAz/ji7ARzz","2cXtfVkE9PQ72BzywKSTJR","2c1J7KDX1Oj5+1gJoUWFW+","2c3eiXcm1Py4ZuGXRoNwiy","2dmiGfn3NCZbnBmNPFCg4/","2du9iKHmRPOqePU0zB5o9+","2d4MSmyhRL/aAVTdIGj3Sx","2ebD9jbeNNvLlELMSqBK+F","2e8th4/3FKf4yocbo4JTHM","2fEhaqtQFGvIC4/LDv0o9w","2fUPdxjvxMtZQXsMvaiBAm","2fbv/2qu5PoYsRSJQqkFP8","30US+wBuNPDYifI7GcVEX2","31RDk2GnFCzZdO0cuvqN9Z","31YSvsDb1EmbODBkTsTVaM","32da32lgFH9qcDHHiks1sy","3220xiwOZClrz4j/0fQ/8m","326wowyWBIM7JlYcu9wM03","33J6tjQR5I0KVzzMXmDO0H","33ickLlzZG3pAn1xliIPNm","33l0ktkHxJ0Lufn7+ass5H","34cL0b/mFBcZtXxTNs1mRS","35Ya0TkxZH3a9+7W9Ma9/5","35fMLUS9lEoqWK7qtHGjT7","35ofoZRQtL7I3xIK2uol1A","35u3W/+xlOb4DqmCQvWPC/","36E+K1V+BEWZeUL6IUdHal","36ltFc8HxI9rmOVsalV4Y8","369Bs73qVDaoWh6u7/vu7G","37y8/BJcZDuaqYVbzqKKkN","37ziBro4lBBIc4rVLSLu4W","37564ROp9K34UkF523QgUp","38UCRIiUZDpYL+FiVJulHo","38bQBPW0lMFKsAswsL4AOI","39lw5OO3pEFpCsala0n0HU","39ynaK0o9M/aIRnpwzrzg7","3a6K4++nlH9IZnV7aommvg","3a+6U3ObNHzZD0xT7buD8s","3b/e10Wz5Mv4qfQT7WZ0Uy","3ctmxR3F5GF4900RXyfO/R","3dc3rLduZK9YqtjwGVMY17","3dxeNwCiFJZKIaZiiq0wuS","3eJm21uBdHbZPW4XYrCfH1","3euFOE1OBG4Zkwa8sq51B0","3e1csZiApBYL2mgcz6KV0N","3fkdA0eXFK6LbbIqA8JL8N","40A7tI5glJDJTpZ6rY63+R","40vRsSQUxFwbriY05uWVnA","40yX7CRiBB75lD8GWJf91j","40/k7BTQhD9ql2r2R9SiV0","41gBBtaqNG5pevu5TOozo8","41p5JuhpdC6ZU2viYu9SAI","41rCERgJ9CKoshBwfYKKa1","411LsROzFLZYwEAqDoY/hC","42EmFrrlFLq7f3MlZCUZj0","43eI9tAJZGr6ifT7kZP2vg","43jathbC1DWown4iSHtJ4E","43xgQgJ2dEy538V19jK0l0","44nFqywxZJn5IuQPLNB2Xm","45XEABThZHZoHC195PGJPE","45mVWMCDVL0JVsIzkWmipx","45os6klOtPup3WTubEDYRp","47GHTeuAhBSaMsNFPovokh","47LfXTNedBhJ5sf0G+5l7j","47WLglnIxMXa4F+J/0wDy3","470V2a5BRAAoDTwrAxgvEN","473GiUzFtFPZuDKntyLC9h","49B6EGEolGKZlJ0wORErgT","49mme5KYVBba46C77DUQgT","49ty0p1jhO8r63nFrJmpUT","4aMEzhQaVCaql2Z4IJfoR2","4adZ6O+XZOF62uqqKjVeL8","4apEkm1eBHeYu6utsCmASh","4aypEO1WxMPLZjBQloYa71","4bAkCs/HVFk712QEvFWySm","4bzx8rQYJPNJO65QLr88bL","4cN+KhmIZGs4WtqPMbeRPh","4cfFvyG/hKhp9LoUwj+Une","4c9yzk11dH67KvKpVzOKXe","4dnbWd/39OSZncicIQSTVn","4fs7u+p2NAkIECvncj+ldN","50hGadhR1B64BEFJBGrNXr","52Is0V+C5BJaVKzGFdHT7b","52XlZmfJlNzohjNBXYVAjc","52r2Hp0yJFDpPrU8Emd4NM","53G+CecBJEEKhitJoWQPFE","53HGoB2XZDcpyJq+yUWI2K","53he3yJ1tGAoh1NX5+of6F","54I+r3IZpGqq8AJvIDsYQw","55v0mTRnpEGaS/lKTFQEfW","57l4ucMShBIYQalFsxgrwb","58QuudqNJCDYlL+oMZomGF","59mSuunflKOpeoGZOzPCmz","5aFWPWsm5Pf5I5CmuXusHi","5aPukilX9NZaSG728PAK2x","5atg/ODLxJ5ZRtLcblykzp","5ay1QkGc1ObrFJXwlf6acn","5bEYn7zT1P3axLdJJC1/qk","5bPf+syZxD2rF+XI05u7k/","5be2WI8Q1OpIGvaeytRKYh","5bs9lnbqFND4SbaUrg+qEN","5b4weL8dtAXLCp+M3hquDb","5cO7kybDxGj4ipyMYdRYZB","5dCes3yhJJa7sGeai0ZGGX","5emaXBP8NFFp0HXER4EVnZ","5eoWwHI0RD360/HecNw4yQ","5ezx8muiFOxp9u/pVuuTNd","5fOmTzu2NFmqkE8St3HojC","5fnbJVtitLcruVIMQJfkLJ","5f1+CU4ARKKZ1j4ZkcrZNE","5f5dyqtRNNxaFmVzYns6FZ","60emOWF79BpavQ3F/PLWB3","60hMW9tSVBQ59R3NJgZMdD","60i3FrmZpAPoGsHUb9He3n","60qrjzNOpAyqhjcOl7aRfx","609Iwu2E1PY7NRLhX6EtxW","60/UUSxpxC26LUUefDOCHn","61KQlbW2FE9rPLgc+nbS05","61YN0QMDdNS5X4IkdCtcD2","61mWkBvJZMCK6OEUuv9Qx7","616wBLmlhFUKsEAQLPY8lk","62JADZ2PpE7Yu9z+GqwbEw","62XsHlRkROMLRlBOMsevWj","62r9VOxxVLII/E/HviqJBe","63Qui10etLUKqsuh7BXpbe","63xtQSx7xC4bEpqDbznl9c","64C9T5KapD8Jepcnu2+UY8","64Jf1D3v1DlovaxBp8s2UI","64lNvw7mtAtILLR0oEIRuh","646jHsgWNBEol7MqVEA0W5","67LYXN0vxE86dHWJBIL/5+","67NfwhE4xBWZlRO34d01pl","69TJcBhUxET6NlHzHYXdOA","69Uegii69BD5+M0GwxF1Ce","69cdura8dFXoIwQpp2qLnu","692nOP5OFMX6lfsPEG0tFP","6aZHOdxopBoqVKpDzxByO3","6a2stTXQlMWKYtsPjlHIlM","6bn9ZrBr5H1rP28r9WKkcu","6cQ5N/+tpJ/qLoFs6J6Z5X","6cWNz/ttpOQrtxTvDsy23e","6cjwQeEX1IDLSQLtM2/kE3","6csx4U8WlGtrmdtcC8PMHs","6c0D3TBqdJTZ5HxeFqjuNk","6dR5c8U2xEPJ9Ujk/chZWr","6dciqS/11F5K7f8WJCghdS","6dyHWw3iZEgZFV/B+oPskn","6eMrHJCntBhbX4Zim/zTZe","6e9JP+C21NTbPsGyKrAckz","6fAgnuYnZC/6vggCDSep9a","6fBWQp3oVG0rCOBmWvfvFg","6fI8BsmINJJ4ykbl0MH7v+","70BfnSAJ9EqLbXbhiKYrqn","70VAr3vrVI3p9b3OkSC9vg","70bmMiNZ9Cb7tnG2TmbsME","70cwRWWOlGXaQq4M7Ta5mI","70iVoWTzRCE4shi+LcoW6C","70xVpgBzhC96wJfoKgAjBa","71AbgMGONIE4DxYqPlNpYG","71LKHuCZZBBbavUSlISWHs","71SJC34mlLpYKMT03xPQs+","71lXUdnP5PwaoQ878/EZvR","71sv6aYvZMLpl9PoHs1VrJ","710n2W49xD+r0+ziEpks4+","72AH+o7b1PobDX9H+HPPZY","72DQfrEIhBbYprnZXwf4VS","72QwD7Q7hAiLMSNOmgBAJm","72u8zEQg1FNJfJvCuzwdeT","73DJqMt2VJjJBEDwaNq+kA","73Hv5WZQhIxbmEnFKMvCcH","73rVTrBgNG+L1C2lowfUmU","74FA3ztCBK5rY8vpQbGmTh","74TaGwXe9J1pIO5C5ugb4A","74tUFVZBpECa05zsDnTlIr","76jhlo/QVCeKBS6LvEpgPl","76oNp3c1tL5rbRx1dU2d6j","76s5OC5dtI/6HnRiEkqV2I","76yRbAEbJCo6ExbXkMDQOM","77WZsjgh1AAYHrbNWHBf/m","778CXse8VOKaRvtcWyR49e","779U9YFbJDg6XoBTeWvw4a","78Un99HHtMJo1xiXtf2r4w","78XyrxmTlITKNCWzJhtLmT","781WYycapAz4UQWhcIO+1/","79mEbiaBBBR6OpHpNbFyHE","79pgCjPENGx657yKSlRsvx","791TdeayhNMbzfdMxC1CKS","7a8L3Bp2xJlLC4NdBa4P2m","7a9L0ehINLoZtL8gVI70L8","7a/QZLET9IDreTiBfRn2PD","7brrDwquhE861Q1S3Gm9IC","7bweOfd5JKB6z/ngUXehHY","7cYQEVHS5Ey7T9Y1ROaljx","7c0tkKrE5IOof/UUYDCMF1","7d/y43nmtLw7UA0ogpshOL","7ePadjx1ZB658SIpK8dRu7","7eSEX43mhO7K0V/PxdFfXR","7ejCRtUC1N65jW5MVQ8phs","7fr/UHo8pKyp3bizwEt88y","7ftryXO2ZNroF8+K7U3SP5","80rjLj4aRA4Zze79mBx4dk","81hnTruXJOb6lle66tawLM","81o9FIDxdDXLmZR8n34hkB","82ILyV315GLYDUDMfJTkKT","82WPTbs6RJGaeufWfJ2+Xb","82kXYsU+ZFFIHHxaEKdTbF","82xBflxP5KRo9dtG5CPmVf","83E5F5u49P94ekFrIgaLLP","834X0XmsJGtp4Qn/gZV5ZF","839cdtLblGRZa551k4SGWY","84DW4RLnhG4L7KX3Ym/EqQ","84px9WcJhAMaw9xlQOa82P","85IauUax5FPar9XAifvQ+6","859rkCITFL4q+Cdp45r4+d","86B/lxoElHrrxnCO/dLlns","86PywkSMNBkYSfObu4p8VU","86aaePS9ZLLp0gYTOPZbnr","86comjJDlELIYFfov/hd+N","86gV0FrHZHLYTfdRd+zX3s","867ZOwUpNMU7jvocl+OXWK","87VxS/hYZJS4vx/2sUJJrl","87YRUhTKhKbaBLOFFuPu7c","87p9V1u95O77cWEGzOh6GT","88xjcgLFlFj7u0HbxfkZOW","88/qbpAvVGaY+MDQN2pt8B","89a1SnfndB8IKHhOzMhfT8","891DjwgiRCAKL3a/yYC9lW","8aCXhpmpRPsZ2YdczVdqla","8aKEA5InxNwpe/osGXn+j5","8bT2GHtQ5Hwb9q+cVHNZtN","8b1rzVAaJIvoOEmAYeYI+9","8cXroL56pMh4utqt65rGiA","8cbsqzX01Fzp91kLFoxZtO","8cqsiqfvdB34iAzJuEYOKz","8cy/sg34tBIa9dV0l62BFt","90N9g1Bp5Cwbe/U8nVoYTV","90f2qTnDlEl6P+1iIAfG8Q","90sSW3F6JIrqK3K8ncskPZ","90wrmR4qhCKLvl7RJ8QK3x","900rOKefpEoInKr7yX1QPS","91TajEtqRDuKdl/2OLAlS6","92C7FxoyBOlank6u4C/f5B","92JcBj/uxHc6LVa9XrE0Ol","93kIk3FnVB3Km8heak79kJ","93t3zIx6JHLpR9t57FCQPL","93ytQPMB5PAIYq0U+e9Dxj","94R5rpCMRFZoVIrIiIthkW","9414u+6o5J045V6o3WBPWM","94/ccDHUZGeoRfwXgbYdgA","95L9nmN5BPMIFDrbEWJ+uf","95MQukO6VNN5zG1x4UOpCL","95VLyuBy9BRII0G2aJwWNk","95zubz+D5DjLLkawmKnqqp","950NW4kMpDEJHhTI+pgdPw","95+XFBNqNLGZOuSNb5w/Fc","97CxGu7hpOQYO8pld2xuT3","97VAuRjEVLbKPVH2uPv1ZB","97oE+WWMJBiINpbiIG5qMs","99BANdxw9FjKRNVotCe7Qz","99OjnFkNdJe5Efa/jazgIL","99bAugbwVDsLxRPAulsDxh","9aKU0ulFtBG5c3U72l23/O","9aekHUK4hKvog/5EBFSW8s","9bEfU+FpBBbIvla3d/bfbY","9bRNSnGVBANb0Xz55Kc2iK","9bYMGoMiVEYrDKV1hM/XNR","9btVuSYNVHz5pwS9G8M7ii","9b5BYoSXhAY7hGUc5QfAxc","9dIoXibodLcqZj5FXzdXjf","9dhGZj9B1E8Lpxl+NN8K+i","9duztOKyVDiI+KUaqxDOqt","9d/6Q3l5pIYI5d7RKM3YKy","9f0bODW9tAh44CFo8YKNDI","a0Fm6B3v9PCrdWE9TBAW6e","a0m9dHffpJFoyN3la0TTmR","a1LGpWMT9CMJuQGqB7uk32","a1cI5RAodJdb/jng4c0Yeq","a1h+FYRP5FF4bfBGQAbJKc","a1osTUSjRAmLL3ThJl16OR","a2MjXRFdtLlYQ5ouAFv/+R","a2OR/gsrlMXqXihnuyKwek","a2qWnswwFLcZ8gsSOZJK5Y","a3oJ+CgghDu77rf2twm7Jk","a37yrbEZpG569YRg3o3GdF","a6AACQqjVFc5aV8I89SLlJ","a6Wnv+RbxN778v/afeGJu6","a6o14BXfxAqIKsM1jTikJR","a7F+/S9xhCwqgPgt2its2E","a7c8fwPxdLKqV6oWVVcrhU","a8NGJ6GzRIF4IgksklPjY/","a8NX2o/KFEf7L4sEdOXkfD","a9hGf3cPNC6L4YIOQDUwrr","a9lX0Nj7hBI7hydaqfXLMI","a9sbrwZiJHnb+ptV41nGRg","aaGo1u11VGy5WWYuzTqOVV","aaVZHaywBIUri8iShfZ1by","abDaXSNbNILr2R23osRP8m","abdOfTAHBHiJd8KtYmV3Ce","acHRHo0TFKR6wpUqO3SDav","acT5GSyzlI9Y7Nkt5CsSuM","acWfPiayJHvIMIiRlCrEHF","ac1JNh/zhB9JGYRhZwj/xy","adKDAzqS1B8KEyTG0SHYp6","adKmgjyO9F7KNGb2Iyf+p2","ad3ayFZwBKvpKntSZQ1I9U","aePFZzLUZIl5etJYjAvVDH","aelnbeiEVJN59NFQKdTzyr","aemNZwnCpMroE6rluVUoEj","afIlV5mgFLRpkHIIIRu2qG","afXPjxG4RKYq9E95/6livD","afar8fFZFKSZjd6oa5dkj8","afjP8HbHVPSJIjlJhnY1rV","b0T+dpMWhJ963RbQxmu6Qb","b1Bn8Ip/BAk7v4Vnw8zXds","b1K+Whv2pLWKHQ9UAX+okR","b1ZMAJy4xLQphdKySmLlXi","b1c1oV6YhIXIFt2ND2yd7P","b1iTmaFKZAUJ2DZ8pET+IE","b1+lK3LhxM3K37MaxE2/mN","b2R2+k6m1CuaqWer7SmjZe","b2XL9oTbBO7LOrOgkLbb/6","b2x0UBP3pI7KvPz7nEPdkf","b2ypnVFEZNkLQbU7n63cjd","b3QGnPWohL/qvMwWM4EfLj","b3mjXKd8VPcKuDhUu5nsif","b4Jj9svi9OAL2U3wocWh5t","b4uciGUmFAi6SP1pS0hFSD","b4wwGkQbxOzZJLdFtU/ZWU","b41dYaGXNJuK8nllVDgNm3","b5iJ69woNMULlT47pdNFIZ","b6wNoAy9NK0rt4kfJZ9C5Q","b60APVQNtDqpaIEaAybypr","b7YZl5d3xAKrkmM5iO+3ag","b8C3QCvn5GuZfPeCBONic9","b8t5ALdztBIJfYZs/eI9i0","b9HiLGhKFJO5RpZbmIrNFg","b9MGiKXv9NsJcczylGdsXZ","b9MnTtvNNE7LK5SHVCuZdE","baTJrRuSBASpdfwGymi9w7","ba35ta+vRDNop8iGy5EgfF","bbrH6hVj1FhYaaZn7R2wU+","bbvtJQbyRDn4sNVv9bpW+P","bb5VeSZWlF6r5hbSiIPxqh","bcA/myCTFH7oFoQm6iXAw2","bdMscuvwBH4rFOt4D7QSDP","bdPXqfJgxEjKMGcesfggOu","bdR58FRHNNyoZuQny0qKqd","bdXuT1EONP/IGBoWccUVX2","bdypfAkJlKBoDYQlqsiM7B","bewx9FlsRPuqoVjZql0h7G","bfMB47ffVEfrLGr5HmlKdR","bfWntJkeRDqLoC5cf7cHGh","c1SYS40sFLEYUKsIVhcR19","c1S9+1nghIjI57RrTgDZkD","c2IhfXlL5Iw5NQeBnB/mTD","c2wfkt7x9KAZAXjTyQVO7c","c2yYuQS1lIIbGlKb+kly2K","c3KoTMRZhDTYctNr1Aawyr","c4QiBi90JODbbU3Te5e+My","c4sUL+bXlFPo7TMH4Ily5o","c4wW84UQlMCaCdC69Quy2x","c4/6VSgIxN3piW2/J4gNks","c5G/u2t0pFCrJdNJshmqcv","c5OiWzqddPn5A7f/6Jhn9l","c5viNMZCVO65MtHg+HztaV","c6km0fZyhJcoGmusDE/KYW","c7u82YvfFApKnwlYSWrgMb","c93n8N2mVOULncZfG8rKKq","cabSvihbhCGrluGPrHOING","cahsXQU9hIJKpBxWnP+MuQ","cbhS3GtFFKUZRU6D0c+7W8","cb8WaMELdPc7yRb+Ho86bw","ccC6L/HktF/J1+bY9f8ROr","ccb8XspjpL4LT/Z0yV008Y","cc5NBTssVKPbJuUJOkrbku","cc/85cRn1CkYyue/k+ntMi","cdfOMgdWpKRI6EDhiJ9oBw","ceZqMl43dAM7U2FAa2PqLG","cebYZO+YVOGrK+G8j7NJ7i","cegMMsGYhCkrIBGtKz70L/","cfaRfSH4ZAxrDiwQYpnM+6","d0QywFzdBJtbVwDJTWPkC7","d0ZwvCfrRMppeddP0HocEC","d1AtYJoS1B06aYBvyePUFn","d1LXn9YOdG+7RUsQAMvFeI","d1OPXIs9xJMKut+8VqORlI","d1VbLQQHZJ0JPJovqQZOcl","d18784eKlML7lfjZ+ghsJh","d2BUW7OKhHk6njKqxFom6p","d2HWC3lvBNRaLrXAEBeAUk","d2OjgLWzhL35hobXbH1OoT","d2VU6WonhJB5YrteF7oRF8","d24UBMUYRD/Yt2EREA1vt+","d29C5fA5JHQbdL/RWnyrhQ","d3ozflQn9M4ZTBiWFGcwCS","d5olwf53FFy5Nrb/KYLM1Z","d63xU80TpNjbG0xHRstzeB","d7OfyyqWpJk48juri7KUuL","d7anaQQ5JMIL4Hl4MOQGjM","d7chmamaRJ4qv7Q8clRWke","d7k++njk9FuYshwGvoimGV","d7taNXItxPi6Q/bm9aFPm9","d75COP6axJC7O5qTXQfMu3","d9AL0FHXhIDYjTCvOjQAnr","d95HJHG7RLl4Phk9NP7x7n","dbMNWDIHJHEYAz+5k66Mxd","dbSoTleuhIQoPx3uSDoFMN","dbfeadKYFHtq+r6LwOdqaE","dbiOOrKEBFELk7RwlLMgvA","dboQIgCVJPyrcy+3LHgCfY","dcsGtQoL5D84cajNLo5p7q","dedpKLDVZG2aTKqVPZaiPU","deh6j2jBBBeICqk+0ofSX/","e0aeTDvCRIe7fQnUfRLQRp","e0qZfpZ35NCJoTSvvjUhrB","e02SL9FrdAvomqKfTdUsXI","e03VM42bVJFIsqA8Yix5cW","e1B9uipaxD+IuCwNCRGpGC","e1ihTBNgtAkrUP//xrTye8","e1w6kR8RZJLKVvdD2T0bqT","e3V08JPQdGl69X0sCylfCU","e3ch9bvX9HeJIDglAOc/AI","e4h/6Q3INNcJBgTAcLpzLn","e4ka2txU5MypqfYTtSTyad","e5BsDboYZEzqP4Os4712YP","e5OshrUzRISKMGfT9WINTf","e5kEkvwC1N9YoPew7i1etW","e5tAL8v71MW5+YOc1FOqCB","e5zwk/7ddBm503vJPIuui2","e6M28kAbRPjLoEMJWHSj98","e6yS5gs9NMH44/yixF6qmT","e6+L+7b+hDn4atU0zuOZuC","e7Nh2s/R9ABKcwiP3a9nqi","e8OoVKiaxG/ZSV8GCXhs1b","e8t6ZQ1SNJDrGEKbhF0HQB","e8+HnqV+NBqoSVecs4ldbW","e95jeB6yRBjLXoqYOGOLbc","e97GVMl6JHh5Ml5qEDdSGa","eaW12FJH9FL7ci5hpB4loU","eaZG8ARRxFgoSMKqbHGyC4","ead8ULB6FIoaOgA5rLNn6v","eaoUkdR35I2rO6r+qmYdUT","ear95P/1NCq4XTa8IFfUaM","eawrN8OB5DXKb8dBiHwCmm","ebBN2jARFJ54VhPXYJNlrX","ebHE6jGkVOP7w3tcpEVCGl","ebVkSfUIJAZoUygUmQPOWY","ecNXzORZZMvKrlh+YfY8/N","ecTpI7/VJMj7F0QN276R2B","ecpdLyjvZBwrvm+cedCcQy","ec1A/l10FMwL7qrU2B0gQz","ec4/L6eQlKaa3+n3aJpawu","edpfVZv2BBO4udo3MLCTzl","edwcIs/cpMG7NraytBr1mO","eeGxy+ajtHxLmPq6pa127W","f0BIwQ8D5Ml7nTNQbh1YlS","f1qnoFeDNIAYvQzs8Lz2Zg","f1yVF5sZlM2ZoY85yjZ8Fw","f2P515Mm1K2pXB9FOJ589W","f2fKrGz9VMToUidBqIn3qM","f3S+1/BItIjJUuuSd+RYle","f6JxBqnzZKxIujEJr2eI39","f6o5OL1SxAoKrhgy6+WpDK","f6v3GUZn9MDIYS5Aq8n602","f7XHeIF6BBCo1o7UK37dFO","f79FRhMrRPLpIBR+HEhdyy","f8BE7dk4tMl6C6muti/05N","f8da0270hPt7eZF1enpe2j","f9Kc+PlGZL/6XC1X8szS1L","f9kzICXcdH3pdS0E+X2RiH","faIFTpgRhCFormKiSwE0zs","faIa/R1zVMebYT7W3+wbyh","fbu5ySFepDuIyi/PlCta4l","fbzfKoqWhLKrTMZWtaG8Pq","fcAhVWPktJEKKtHUPd32TQ","fcFLTFMHFMXrfn3KK96mdI","fcHdfvqVFNPqYNnuRWPqu9","fcjQl4ZgNNWJ9c1oRY2w9h","fct0Z142VCwJrMBYVC2Gmv","feGDsVvFRK8bC/ocWZoO8I","feTARaR5JAB5bgd7u3C6At","feyyvlgTRBm7nBSAoO3iFT","ffAR7yJkFJ9LU085xKaUoV","ffPIHHIFJOAoSeegpMHdGt"],"scenes":{"db://assets/games/1113_Slot_Pharaoh/1113.fire":216},"redirect":[335,0,530,1,620,0,778,0,790,1,796,0],"deps":["resources","internal"],"packs":{"0dca08d16":[225,226,227,119,228,120,229,230,231,232,233,234,0,235,236,237,1,238,239,240,2,121,241,122,123,242,3,243,244,4,245,246,247,248,249,250,5,251,252,253,254,124,255,256,257,258,125,259,260,261,6,262,263,126,264,265,7,266,8,267,268,269,270,271,272,273,9,274,275,276,127,277,10,278,279,128,280,281,282,283,11,284,285,286,287,288,289,129,290,12,291,130,292,293,131,294,295,13,296,132,133,297,298,134,299,300,301,302,303,135,304,305,306,307,14,136,308,309,310,311,312,313,314,315,316,15,16,317,318,319,320,321,322,323,324,17,325,326,327,328,329,330,18,331,19,332,333,20,334,336,337,338,339,340,341,21,342,137,343,344,345,346,347,348,349,350,351,352,138,22,139,353,140,354,355,356,357,358,359,360,361,23,362,363,364,365,366,24,367,25,141,368,369,142,370,371,372,143,373,374,144,375,376,26,27,377,378,28,379,145,146,380,29,381,382,383,384,30,385,386,387,388,389,390,391,392,393,394,395,31,396,397,32,398,33,147,34,399,148,35,400,149,401,402,403,150,404,405,406,407,408,36,409,410,411,151,412,413,414,37,415,416,417,38,418,419,420,421,422,39,423,152,424,40,425,41,426,427,428,429,42,43,430,44,45,46,47,431,432,153,154,433,155,434,435,436,437,48,156,438,439,49,440,441,442,443,444,445,446,447,448,449,450,451,452,453,454,455,456,457,157,458,459,158,460,50,461,462,463,464,159,465,51,466,160,161,467,468,469,470,471,472,473,474,475,476,52,477,162,163,478,164,165,479,480,481,482,483,484,485,486,53,487,488,54,489,490,491,492,166,493,494,495,496,497,498,499,500,501,502,503,504,505,506,167,507,508,509,510,168,511,512,513,514,55,169,515,516,517,518,519,56,520,521,522,523,57,524,170,525,526,58,527,171,528,529,531,532,172,173,533,534,59,535,536,537,538,60,539,540,61,541,174,542,62,543,63,544,545,546,547,548,64,175,65,549,550,551,552,553,176,554,555,556,557,558,559,177,560,561,562,563,564,565,178,566,179,567,568,569,180,570,181,66,571,572,573,574,67,575,576,577,578,579,580,581,68,182,582,583,584,585,586,587,588,589,590,591,592,593,594,595,596,597,598,599,600,601,69,602,183,603,184,604,605,606,70,607,608,185,71,72,609,610,611,612,613,614,615,616,73,186,617,74,618,187,619,621,622,188,623,624,625,626,627,75,628,629,630,631,189,632,633,634,635,636,190,191,637,638,76,639,640,641,642,192,77,643,644,645,646,647,648,78,649,650,651,652,193,653,194,654,655,656,657,658,195,659,660,661,196,662,663,197,664,665,666,198,79,667,668,669,80,670,671,672,673,674,199,675,81,676,677,678,82,83,679,680,681,682,683,684,685,686,687,688,689,84,690,691,692,85,86,200,87,693,694,88,89,695,696,697,90,698,699,700,701,702,703,704,91,705,201,706,707,202,203,708,709,710,711,204,712,713,205,206,714,715,716,92,717,93,207,94,95,718,719,720,721,96,722,723,97,208,724,725,726,727,98,728,729,730,731,732,209,99,100,733,734,735,210,736,211,737,738,739,740,741,742,743,744,101,745,102,212,103,746,747,748,749,213,750,751,104,105,752,753,214,215,754,755,756,757,758,759,760,216,106,107,761,762,763,764,765,766,767,768,769,108,770,771,772,109,773,774,775,776,217,777,110,779,780,781,782,783,218,784,111,785,786,219,787,220,112,113,788,789,791,792,793,794,795,221,114,222,797,798,115,799,800,223,801,116,802,803,804,805,806,807,808,224,809,810,811,812,117,813,814,815,816,817,818,819,820,821,118,822,823,824]},"name":"1113","importBase":"import","nativeBase":"native","debug":false,"isZip":false,"encrypted":false,"versions":{"import":["0dca08d16","2d700"],"native":[0,"2a3b6",1,"ad14e",2,"706fd",3,"b8430",4,"79339",5,"56356",6,"8e09f",7,"ea14d",8,"2f5bd",9,"77701",10,"bfb72",11,"be726",12,"32958",13,"35413",14,"538a3",15,"f006e",16,"6ff8e",17,"dc2f0",18,"e45e7",19,"d73db",20,"13b8f",21,"d28bb",22,"465ea",23,"f29e3",24,"3ebb6",25,"a797b",26,"4bfc6",27,"37a28",28,"09e16",29,"1549a",30,"b14f1",31,"bd7f7",32,"3bd54",33,"03aa1",34,"64f38",35,"937ce",36,"daf65",37,"295b3",38,"949e4",39,"4d796",40,"2711f",41,"0f245",42,"f1570",43,"633b6",44,"87c4d",45,"32437",46,"9a21a",47,"14482",48,"0a8db",49,"5f416",158,"6d707",50,"8c899",51,"c078b",52,"ae9a9",53,"dae4c",54,"ff84c",166,"d730f",55,"48c0e",56,"ab468",57,"107c3",58,"80faa",59,"dc524",60,"b6aad",61,"1eafc",62,"f262f",63,"6dbf0",64,"36cd1",65,"98787",66,"ac8f7",67,"66d4a",68,"286a6",182,"b5d2b",69,"d0af0",70,"d28aa",71,"c4d8e",72,"fb3c5",73,"ccc95",74,"0468f",75,"3c1af",76,"ca50e",77,"83c96",78,"b6840",196,"2bf0b",79,"98e08",80,"546cf",81,"fad36",82,"ae21a",83,"44f11",84,"de86b",85,"7ecb4",86,"956e3",87,"50276",88,"edf8f",89,"55e25",90,"83fcc",91,"8e85e",206,"7ecb4",92,"856d3",93,"13f12",94,"c8867",95,"005bc",96,"4d8a9",97,"2dd21",208,"841f5",98,"ebeb3",99,"5735d",100,"a65a2",211,"d55c2",101,"d16d9",102,"bed45",103,"44df6",104,"70a02",105,"f55f5",106,"a7d79",107,"51f18",108,"36c34",109,"b2114",110,"7295f",111,"3846a",112,"2fff2",113,"aded7",114,"d66fa",115,"26e9c",116,"c4646",117,"a4ee6",118,"5a4a2"]}}